setup.py
pyquiz/__init__.py
pyquiz/__main__.py
pyquiz/question.py
pyquiz/quizbuilder.py
pyquiz/render.py
pyquiz.egg-info/PKG-INFO
pyquiz.egg-info/SOURCES.txt
pyquiz.egg-info/dependency_links.txt
pyquiz.egg-info/entry_points.txt
pyquiz.egg-info/requires.txt
pyquiz.egg-info/top_level.txt