Metadata-Version: 1.0
Name: pyquiz
Version: 0.0.1
Summary: Library for writing Python language quizes
Home-page: https://github.com/thomasballinger/pythonquiz
Author: Tom Ballinger
Author-email: thomasballinger@gmail.com
License: MIT
Platform: UNKNOWN
